MercadoBitcoinBalance/__init__.py
MercadoBitcoinBalance/__main__.py
mercadobitcoinbalance-1.5.dist-info/LICENSE
mercadobitcoinbalance-1.5.dist-info/METADATA
mercadobitcoinbalance-1.5.dist-info/WHEEL
mercadobitcoinbalance-1.5.dist-info/entry_points.txt
mercadobitcoinbalance-1.5.dist-info/top_level.txt
mercadobitcoinbalance-1.5.dist-info/RECORD
