Metadata-Version: 2.2
Name: MercadoBitcoinBalance
Version: 1.5
Summary: Calcula, salva e reporta seu saldo do Mercado Bitcoin
Author-email: Avi Alkalay <avi@unix.sh>
License:                     GNU GENERAL PUBLIC LICENSE
Project-URL: Homepage, https://github.com/avibrazil/MercadoBitcoinBalance
Project-URL: Source, https://github.com/avibrazil/MercadoBitcoinBalance
Project-URL: Issues, https://github.com/avibrazil/MercadoBitcoinBalance/issues/new/choose
Project-URL: Pypi, https://pypi.org/project/MercadoBitcoinBalance
Keywords: etl,crypto,mercadobitcoin
Classifier: Programming Language :: Python :: 3
Classifier: Operating System :: OS Independent
Classifier: License :: OSI Approved :: GNU Library or Lesser General Public License (LGPL)
Classifier: Development Status :: 5 - Production/Stable
Classifier: Intended Audience :: Science/Research
Classifier: Topic :: Scientific/Engineering :: Information Analysis
Requires-Python: >=3.8
License-File: LICENSE
Requires-Dist: pandas
